autodl/__init__.py
autodl/autodl_elastic_deployment.py
autodl_api-1.0.2.dist-info/licenses/LICENSE
autodl_api-1.0.2.dist-info/METADATA
autodl_api-1.0.2.dist-info/WHEEL
autodl_api-1.0.2.dist-info/top_level.txt
autodl_api-1.0.2.dist-info/RECORD
