Metadata-Version: 2.4
Name: autodl-api
Version: 1.0.2
Summary: AutoDL弹性部署API封装类，支持所有弹性部署相关功能
Author-email: Rookie <RookieEmail@163.com>
License-Expression: MIT
Project-URL: Homepage, https://github.com/Rookie-Package/autodl.git
Project-URL: Documentation, https://github.com/Rookie-Package/autodl.git
Project-URL: Repository, https://github.com/Rookie-Package/autodl.git
Project-URL: Bug Tracker, https://github.com/Rookie-Package/autodl/issues
Classifier: Development Status :: 4 - Beta
Classifier: Intended Audience :: Developers
Classifier: Operating System :: OS Independent
Classifier: Programming Language :: Python :: 3
Classifier: Programming Language :: Python :: 3.7
Classifier: Programming Language :: Python :: 3.8
Classifier: Programming Language :: Python :: 3.9
Classifier: Programming Language :: Python :: 3.10
Classifier: Programming Language :: Python :: 3.11
Classifier: Topic :: Software Development :: Libraries :: Python Modules
Classifier: Topic :: Internet :: WWW/HTTP :: Dynamic Content
Requires-Python: >=3.7
License-File: LICENSE
Requires-Dist: requests>=2.25.0
Provides-Extra: dev
Requires-Dist: pytest>=6.0; extra == "dev"
Requires-Dist: pytest-cov>=2.0; extra == "dev"
Requires-Dist: black>=21.0; extra == "dev"
Requires-Dist: flake8>=3.8; extra == "dev"
Dynamic: license-file
